moolam/arichuvadi.py
moolam/orunguri-tha.py
arichuvadi-0.0.2.dist-info/LICENSE
arichuvadi-0.0.2.dist-info/METADATA
arichuvadi-0.0.2.dist-info/WHEEL
arichuvadi-0.0.2.dist-info/top_level.txt
arichuvadi-0.0.2.dist-info/RECORD
