Metadata-Version: 2.1
Name: arichuvadi
Version: 0.0.2
Summary: a basic set of tools to work with Tamil text
Author-email: vanangamudi <selva.developer@gmail.com>
License: GNU GENERAL PUBLIC LICENSE
Project-URL: Homepage, https://github.com/vanangamudi/arichuvadi
Project-URL: Bug Tracker, https://github.com/vanangamudi/arichuvadi/issues
Classifier: Programming Language :: Python :: 3
Classifier: Operating System :: OS Independent
Requires-Python: >=3.5
License-File: LICENSE
